dcsi/__init__.py
dcsi/_modidx.py
dcsi/core.py
dcsi/helper.py
dcsi-0.0.1.dist-info/LICENSE
dcsi-0.0.1.dist-info/METADATA
dcsi-0.0.1.dist-info/WHEEL
dcsi-0.0.1.dist-info/entry_points.txt
dcsi-0.0.1.dist-info/top_level.txt
dcsi-0.0.1.dist-info/RECORD
