Metadata-Version: 2.1
Name: dcsi
Version: 0.0.1
Summary: A helper app for Data, Code, and Social Innovation taught at Lincoln Alexander Law School
Home-page: https://github.com/simon-lawyer/dcsi
Author: Simon Wallace
Author-email: simonwallace@osgoode.yorku.ca
License: Apache Software License 2.0
Keywords: nbdev jupyter notebook python
Classifier: Development Status :: 4 - Beta
Classifier: Intended Audience :: Developers
Classifier: Natural Language :: English
Classifier: Programming Language :: Python :: 3.7
Classifier: Programming Language :: Python :: 3.8
Classifier: Programming Language :: Python :: 3.9
Classifier: Programming Language :: Python :: 3.10
Classifier: License :: OSI Approved :: Apache Software License
Requires-Python: >=3.7
License-File: LICENSE
Requires-Dist: pandas
Provides-Extra: dev
